{
  "users": [
    {
      "id": "Md75lpAe",
      "name": "Lavi Singh",
      "email": "ajayk@reliablegroup.com",
      "password": "ryter"
    },
    {
      "id": "cwg3jFk5",
      "name": "fnkldfnl",
      "email": "ajayk@reliablegroup.com",
      "password": "sad"
    },
    {
      "id": "ionudm4t",
      "name": "Lavi Singh",
      "email": "ajayk@reliablegroup.com",
      "password": "vdg"
    },
    {
      "id": "8NfHd4x7",
      "name": "Lavi Singh",
      "email": "ajayk@reliablegroup.com",
      "password": "vdg"
    },
    {
      "id": "f-wVXTSX",
      "name": "fnkldfnl",
      "email": "ajayk@reliablegroup.com",
      "password": "fsafda"
    }
  ]
}